Workbook

Sheet Summary
B2: datacore.com.sa — improvement register
B3: 141 items. Filter the Improvements sheet by Impact to plan a phase.
B4: Basis: 'Seen' = observed in your screen recording · 'Measured' = calculated · 'Verify' = needs checking against the live code · 'Planning' = new work.
B6: Area | C6: High | D6: Med | E6: Low | F6: Total
B7: Accessibility | C7: =COUNTIFS(Improvements!$B$2:$B$142,$B7,Improvements!$F$2:$F$142,C$6) -> 6 | D7: =COUNTIFS(Improvements!$B$2:$B$142,$B7,Improvements!$F$2:$F$142,D$6) -> 11 | E7: =COUNTIFS(Improvements!$B$2:$B$142,$B7,Improvements!$F$2:$F$142,E$6) -> 1 | F7: =SUM(C7:E7) -> 18
B8: Typography | C8: =COUNTIFS(Improvements!$B$2:$B$142,$B8,Improvements!$F$2:$F$142,C$6) -> 1 | D8: =COUNTIFS(Improvements!$B$2:$B$142,$B8,Improvements!$F$2:$F$142,D$6) -> 6 | E8: =COUNTIFS(Improvements!$B$2:$B$142,$B8,Improvements!$F$2:$F$142,E$6) -> 3 | F8: =SUM(C8:E8) -> 10
B9: Layout | C9: =COUNTIFS(Improvements!$B$2:$B$142,$B9,Improvements!$F$2:$F$142,C$6) -> 3 | D9: =COUNTIFS(Improvements!$B$2:$B$142,$B9,Improvements!$F$2:$F$142,D$6) -> 8 | E9: =COUNTIFS(Improvements!$B$2:$B$142,$B9,Improvements!$F$2:$F$142,E$6) -> 4 | F9: =SUM(C9:E9) -> 15
B10: Navigation | C10: =COUNTIFS(Improvements!$B$2:$B$142,$B10,Improvements!$F$2:$F$142,C$6) -> 3 | D10: =COUNTIFS(Improvements!$B$2:$B$142,$B10,Improvements!$F$2:$F$142,D$6) -> 4 | E10: =COUNTIFS(Improvements!$B$2:$B$142,$B10,Improvements!$F$2:$F$142,E$6) -> 3 | F10: =SUM(C10:E10) -> 10
B11: Conversion | C11: =COUNTIFS(Improvements!$B$2:$B$142,$B11,Improvements!$F$2:$F$142,C$6) -> 6 | D11: =COUNTIFS(Improvements!$B$2:$B$142,$B11,Improvements!$F$2:$F$142,D$6) -> 7 | E11: =COUNTIFS(Improvements!$B$2:$B$142,$B11,Improvements!$F$2:$F$142,E$6) -> 1 | F11: =SUM(C11:E11) -> 14
B12: Content | C12: =COUNTIFS(Improvements!$B$2:$B$142,$B12,Improvements!$F$2:$F$142,C$6) -> 5 | D12: =COUNTIFS(Improvements!$B$2:$B$142,$B12,Improvements!$F$2:$F$142,D$6) -> 8 | E12: =COUNTIFS(Improvements!$B$2:$B$142,$B12,Improvements!$F$2:$F$142,E$6) -> 1 | F12: =SUM(C12:E12) -> 14
B13: Services | C13: =COUNTIFS(Improvements!$B$2:$B$142,$B13,Improvements!$F$2:$F$142,C$6) -> 1 | D13: =COUNTIFS(Improvements!$B$2:$B$142,$B13,Improvements!$F$2:$F$142,D$6) -> 4 | E13: =COUNTIFS(Improvements!$B$2:$B$142,$B13,Improvements!$F$2:$F$142,E$6) -> 1 | F13: =SUM(C13:E13) -> 6
B14: Projects | C14: =COUNTIFS(Improvements!$B$2:$B$142,$B14,Improvements!$F$2:$F$142,C$6) -> 3 | D14: =COUNTIFS(Improvements!$B$2:$B$142,$B14,Improvements!$F$2:$F$142,D$6) -> 3 | E14: =COUNTIFS(Improvements!$B$2:$B$142,$B14,Improvements!$F$2:$F$142,E$6) -> 1 | F14: =SUM(C14:E14) -> 7
B15: Contact | C15: =COUNTIFS(Improvements!$B$2:$B$142,$B15,Improvements!$F$2:$F$142,C$6) -> 1 | D15: =COUNTIFS(Improvements!$B$2:$B$142,$B15,Improvements!$F$2:$F$142,D$6) -> 6 | E15: =COUNTIFS(Improvements!$B$2:$B$142,$B15,Improvements!$F$2:$F$142,E$6) -> 1 | F15: =SUM(C15:E15) -> 8
B16: Performance | C16: =COUNTIFS(Improvements!$B$2:$B$142,$B16,Improvements!$F$2:$F$142,C$6) -> 5 | D16: =COUNTIFS(Improvements!$B$2:$B$142,$B16,Improvements!$F$2:$F$142,D$6) -> 6 | E16: =COUNTIFS(Improvements!$B$2:$B$142,$B16,Improvements!$F$2:$F$142,E$6) -> 0 | F16: =SUM(C16:E16) -> 11
B17: SEO | C17: =COUNTIFS(Improvements!$B$2:$B$142,$B17,Improvements!$F$2:$F$142,C$6) -> 5 | D17: =COUNTIFS(Improvements!$B$2:$B$142,$B17,Improvements!$F$2:$F$142,D$6) -> 5 | E17: =COUNTIFS(Improvements!$B$2:$B$142,$B17,Improvements!$F$2:$F$142,E$6) -> 1 | F17: =SUM(C17:E17) -> 11
B18: Localisation | C18: =COUNTIFS(Improvements!$B$2:$B$142,$B18,Improvements!$F$2:$F$142,C$6) -> 3 | D18: =COUNTIFS(Improvements!$B$2:$B$142,$B18,Improvements!$F$2:$F$142,D$6) -> 3 | E18: =COUNTIFS(Improvements!$B$2:$B$142,$B18,Improvements!$F$2:$F$142,E$6) -> 1 | F18: =SUM(C18:E18) -> 7
... B20: Analytics | C20: =COUNTIFS(Improvements!$B$2:$B$142,$B20,Improvements!$F$2:$F$142,C$6) -> 3 | D20: =COUNTIFS(Improvements!$B$2:$B$142,$B20,Improvements!$F$2:$F$142,D$6) -> 2 | E20: =COUNTIFS(Improvements!$B$2:$B$142,$B20,Improvements!$F$2:$F$142,E$6) -> 0 | F20: =SUM(C20:E20) -> 5
B21: Total | C21: =SUM(C7:C20) -> 47 | D21: =SUM(D7:D20) -> 76 | E21: =SUM(E7:E20) -> 18 | F21: =SUM(F7:F20) -> 141
B23: Suggested phasing
B24: Phase 1 — week 1 | C24: Every High-impact / Small-effort item. Contrast fix, chat widget, hero rewrite, the three layout bugs, tel: links, WhatsApp.
B26: Phase 2 — weeks 2–5 | C26: Typography unification, service page content rewrite, projects template and filters, performance pass, SEO foundations.
B28: Phase 3 — weeks 4–10 | C28: Products catalogue and RFQ module, admin panel, Excel import.
B30: Phase 4 — after launch | C30: Arabic site, location landing pages, project photography.

Sheet Improvements
A1: # | B1: Area | C1: Where | D1: What's wrong | E1: What to do | F1: Impact | G1: Effort | H1: Basis | I1: Owner | J1: Done
A2: 1 | B2: Accessibility | C2: Site-wide | D2: Brand teal #13BEA0 on white measures 2.36:1. WCAG AA needs 4.5:1 for text, 3:1 for controls. | E2: Introduce #07806B as the interactive teal for all text and button fills. Keep #13BEA0 for logo, icons and decorative fills only. | F2: High | G2: S | H2: Measured
A3: 2 | B3: Accessibility | C3: Hero, all pages | D3: White 'GET IN TOUCH' label on the teal button is 2.36:1 — unreadable in daylight on a phone. | E3: Either darken the fill to #07806B and keep white text (4.87:1), or keep the bright teal and set the label to #18191E (7.44:1). | F3: High | G3: S | H3: Measured
A4: 3 | B4: Accessibility | C4: Main nav | D4: Active page is signalled by teal colour alone, and that teal fails contrast. | E4: Add a weight change or solid underline so the active state does not depend on colour. | F4: High | G4: S | H4: Seen
A5: 4 | B5: Accessibility | C5: Site-wide | D5: No visible keyboard focus indicator observed. | E5: Add a :focus-visible outline of 2px in #07806B with 2px offset on every interactive element. | F5: High | G5: S | H5: Verify
A6: 5 | B6: Accessibility | C6: Services mega-menu | D6: Menu appears to open on hover only, which excludes keyboard and touch users. | E6: Open on click and Enter, close on Escape, and manage focus into the panel. | F6: High | G6: M | H6: Verify
A7: 6 | B7: Accessibility | C7: Home hero | D7: Headline sits directly on a photograph with no scrim, so contrast depends on which image loads. | E7: Add a gradient overlay behind the text block so contrast holds for any hero image. | F7: High | G7: S | H7: Seen
A8: 7 | B8: Accessibility | C8: Home hero | D8: Carousel auto-rotates with no pause control (WCAG 2.2.2). | E8: Remove the carousel, or add a visible pause and honour prefers-reduced-motion. | F8: Med | G8: S | H8: Seen
A9: 8 | B9: Accessibility | C9: Section headings | D9: Giant ghosted watermark words are real text, so screen readers announce 'SERVICE SERVICE'. | E9: Mark them aria-hidden, or render as a background image. | F9: Med | G9: S | H9: Seen
A10: 9 | B10: Accessibility | C10: Site-wide | D10: No skip-to-content link. | E10: Add a visually hidden skip link as the first focusable element. | F10: Med | G10: S | H10: Verify
A11: 10 | B11: Accessibility | C11: Forms | D11: Fields may rely on placeholder text instead of persistent labels. | E11: Give every field a visible label that stays after the user types. | F11: Med | G11: S | H11: Verify
A12: 11 | B12: Accessibility | C12: Carousel controls | D12: Prev/next arrows are small, unlabelled and likely under the 44px minimum target. | E12: Add aria-labels and enlarge hit areas to 44x44px. | F12: Med | G12: S | H12: Seen
A13: 12 | B13: Accessibility | C13: Logo marquee | D13: Continuously auto-scrolling logo strip with no pause. | E13: Pause on hover and on focus, and stop entirely under prefers-reduced-motion. | F13: Med | G13: S | H13: Seen
... A142: 141 | B142: Analytics | C142: Site-wide | D142: No baseline before the redesign. | E142: Capture four weeks of baseline metrics before shipping changes. | F142: High | G142: S | H142: Planning
